[
  {
    "dept": "1185283",
    "deptName": "정보통신공학과",
    "sno": "GEB1112-001",
    "subject": "크로스오버 1 : 인간의 탐색",
    "grade": "1",
    "credit": "2.0",
    "category": "교양필수",
    "time": "월4,월5,월6,월7",
    "place": "60주년-101",
    "detail_place": "월4,5,6,7(60주년-101)",
    "name_pf": "정연재",
    "rate": "Pass/Fail",
    "isWeb": false,
    "bigo": "이공계열 학생 수강,"
  },
  {
    "dept": "1185283",
    "deptName": "정보통신공학과",
    "sno": "GEB1112-002",
    "subject": "크로스오버 1 : 인간의 탐색",
    "grade": "1",
    "credit": "2.0",
    "category": "교양필수",
    "time": "월9,월10,월11,월12",
    "place": "60주년-101",
    "detail_place": "월9,10,11,12(60주년-101)",
    "name_pf": "정연재",
    "rate": "Pass/Fail",
    "isWeb": false,
    "bigo": "이공계열 학생 수강,"
  },
  {
    "dept": "1185283",
    "deptName": "정보통신공학과",
    "sno": "GEB1112-003",
    "subject": "크로스오버 1 : 인간의 탐색",
    "grade": "1",
    "credit": "2.0",
    "category": "교양필수",
    "time": "월4,월5,월6,월7",
    "place": "60주년-107",
    "detail_place": "월4,5,6,7(60주년-107)",
    "name_pf": "도윤정",
    "rate": "Pass/Fail",
    "isWeb": false,
    "bigo": "이공계열 학생 수강,"
  },
  {
    "dept": "1185283",
    "deptName": "정보통신공학과",
    "sno": "GEB1112-004",
    "subject": "크로스오버 1 : 인간의 탐색",
    "grade": "1",
    "credit": "2.0",
    "category": "교양필수",
    "time": "월9,월10,월11,월12",
    "place": "60주년-107",
    "detail_place": "월9,10,11,12(60주년-107)",
    "name_pf": "도윤정",
    "rate": "Pass/Fail",
    "isWeb": false,
    "bigo": "이공계열 학생 수강,"
  },
  {
    "dept": "1185283",
    "deptName": "정보통신공학과",
    "sno": "GEB1112-005",
    "subject": "크로스오버 1 : 인간의 탐색",
    "grade": "1",
    "credit": "2.0",
    "category": "교양필수",
    "time": "월9,월10,월11,월12",
    "place": "60주년-201",
    "detail_place": "월9,10,11,12(60주년-201)",
    "name_pf": "정영진",
    "rate": "Pass/Fail",
    "isWeb": false,
    "bigo": "이공계열 학생 수강,"
  },
  {
    "dept": "1185283",
    "deptName": "정보통신공학과",
    "sno": "GEB1112-006",
    "subject": "크로스오버 1 : 인간의 탐색",
    "grade": "1",
    "credit": "2.0",
    "category": "교양필수",
    "time": "월4,월5,월6,월7",
    "place": "60주년-206",
    "detail_place": "월4,5,6,7(60주년-206)",
    "name_pf": "성동기",
    "rate": "Pass/Fail",
    "isWeb": false,
    "bigo": "이공계열 학생 수강,"
  },
  {
    "dept": "1185283",
    "deptName": "정보통신공학과",
    "sno": "GEB1112-007",
    "subject": "크로스오버 1 : 인간의 탐색",
    "grade": "1",
    "credit": "2.0",
    "category": "교양필수",
    "time": "월9,월10,월11,월12",
    "place": "60주년-206",
    "detail_place": "월9,10,11,12(60주년-206)",
    "name_pf": "성동기",
    "rate": "Pass/Fail",
    "isWeb": false,
    "bigo": "이공계열 학생 수강,"
  },
  {
    "dept": "1185283",
    "deptName": "정보통신공학과",
    "sno": "GEB1112-008",
    "subject": "크로스오버 1 : 인간의 탐색",
    "grade": "1",
    "credit": "2.0",
    "category": "교양필수",
    "time": "화4,화5,화6,화7",
    "place": "60주년-207",
    "detail_place": "화4,5,6,7(60주년-207)",
    "name_pf": "정연재",
    "rate": "Pass/Fail",
    "isWeb": false,
    "bigo": "이공계열 학생 수강,"
  },
  {
    "dept": "1185283",
    "deptName": "정보통신공학과",
    "sno": "GEB1112-009",
    "subject": "크로스오버 1 : 인간의 탐색",
    "grade": "1",
    "credit": "2.0",
    "category": "교양필수",
    "time": "수9,수10,수11,수12",
    "place": "60주년-207",
    "detail_place": "수9,10,11,12(60주년-207)",
    "name_pf": "정영진",
    "rate": "Pass/Fail",
    "isWeb": false,
    "bigo": "이공계열 학생 수강,"
  },
  {
    "dept": "1185283",
    "deptName": "정보통신공학과",
    "sno": "GEB1112-010",
    "subject": "크로스오버 1 : 인간의 탐색",
    "grade": "1",
    "credit": "2.0",
    "category": "교양필수",
    "time": "화20,화21,화22,화23",
    "place": "60주년-206",
    "detail_place": "화20,21,22,23(60주년-206)",
    "name_pf": "성동기",
    "rate": "Pass/Fail",
    "isWeb": false,
    "bigo": "미래융합대학 분반,"
  },
  {
    "dept": "1185283",
    "deptName": "정보통신공학과",
    "sno": "ACE1313-001",
    "subject": "객체지향프로그래밍 1",
    "grade": "전체",
    "credit": "3.0",
    "category": "교양필수",
    "time": "월4,월5,월6,월7,목1,목2,목3,목4",
    "place": "하-422",
    "detail_place": "월4,5,6,7,목1,2,3,4(하-422)",
    "name_pf": "김유성",
    "rate": "상대평가",
    "isWeb": false,
    "bigo": ""
  },
  {
    "dept": "1185283",
    "deptName": "정보통신공학과",
    "sno": "ACE1313-002",
    "subject": "객체지향프로그래밍 1",
    "grade": "전체",
    "credit": "3.0",
    "category": "교양필수",
    "time": "화7,화8,화9,화10,수4,수5,수6,수7",
    "place": "하-422",
    "detail_place": "화7,8,9,10,수4,5,6,7(하-422)",
    "name_pf": "최학남",
    "rate": "상대평가",
    "isWeb": false,
    "bigo": ""
  },
  {
    "dept": "1185283",
    "deptName": "정보통신공학과",
    "sno": "ACE1313-003",
    "subject": "객체지향프로그래밍 1",
    "grade": "전체",
    "credit": "3.0",
    "category": "교양필수",
    "time": "화13,화14,화15,화16,수10,수11,수12,수13",
    "place": "하-422",
    "detail_place": "화13,14,15,16,수10,11,12,13(하-422)",
    "name_pf": "최학남",
    "rate": "상대평가",
    "isWeb": false,
    "bigo": ""
  },
  {
    "dept": "1185283",
    "deptName": "정보통신공학과",
    "sno": "ACE1313-004",
    "subject": "객체지향프로그래밍 1",
    "grade": "전체",
    "credit": "3.0",
    "category": "교양필수",
    "time": "월19,월20,월21,월22,목19,목20,목21,목22",
    "place": "하-424",
    "detail_place": "월19,20,21,22,목19,20,21,22(하-424)",
    "name_pf": "김민철",
    "rate": "상대평가",
    "isWeb": false,
    "bigo": ""
  },
  {
    "dept": "1185283",
    "deptName": "정보통신공학과",
    "sno": "ACE1313-005",
    "subject": "객체지향프로그래밍 1",
    "grade": "전체",
    "credit": "3.0",
    "category": "교양필수",
    "time": "수19,수20,수21,수22,금19,금20,금21,금22",
    "place": "하-422",
    "detail_place": "수19,20,21,22,금19,20,21,22(하-422)",
    "name_pf": "김민철",
    "rate": "상대평가",
    "isWeb": false,
    "bigo": ""
  },
  {
    "dept": "1185283",
    "deptName": "정보통신공학과",
    "sno": "ACE2101-023",
    "subject": "공업수학 1",
    "grade": "전체",
    "credit": "3.0",
    "category": "교양필수",
    "time": "월16,월17,월18,월19,월20,월21",
    "place": "5동106B",
    "detail_place": "월16,17,18,19,20,21(5동106B)",
    "name_pf": "정찬석",
    "rate": "상대평가",
    "isWeb": false,
    "bigo": "선수,"
  },
  {
    "dept": "1185283",
    "deptName": "정보통신공학과",
    "sno": "ACE2101-024",
    "subject": "공업수학 1",
    "grade": "전체",
    "credit": "3.0",
    "category": "교양필수",
    "time": "금13,금14,금15,금16,금17,금18",
    "place": "5동107B",
    "detail_place": "금13,14,15,16,17,18(5동107B)",
    "name_pf": "최경표",
    "rate": "상대평가",
    "isWeb": false,
    "bigo": "선수,"
  },
  {
    "dept": "1185283",
    "deptName": "정보통신공학과",
    "sno": "ACE2105-005",
    "subject": "선형대수",
    "grade": "전체",
    "credit": "3.0",
    "category": "교양필수",
    "time": "수4,수5,수6,금10,금11,금12",
    "place": "하-232",
    "detail_place": "수4,5,6,금10,11,12(하-232)",
    "name_pf": "김춘우",
    "rate": "상대평가",
    "isWeb": false,
    "bigo": "선수,"
  },
  {
    "dept": "1185283",
    "deptName": "정보통신공학과",
    "sno": "ACE2105-006",
    "subject": "선형대수",
    "grade": "전체",
    "credit": "3.0",
    "category": "교양필수",
    "time": "화4,화5,화6,목4,목5,목6",
    "place": "하-232",
    "detail_place": "화4,5,6,목4,5,6(하-232)",
    "name_pf": "박인규",
    "rate": "상대평가",
    "isWeb": false,
    "bigo": "선수,"
  },
  {
    "dept": "1185283",
    "deptName": "정보통신공학과",
    "sno": "ACE2105-007",
    "subject": "선형대수",
    "grade": "전체",
    "credit": "3.0",
    "category": "교양필수",
    "time": "월1,월2,월3,화1,화2,화3",
    "place": "하-232",
    "detail_place": "월1,2,3,화1,2,3(하-232)",
    "name_pf": "박대영",
    "rate": "상대평가",
    "isWeb": false,
    "bigo": "선수,"
  },
  {
    "dept": "1185283",
    "deptName": "정보통신공학과",
    "sno": "MTH1001-029",
    "subject": "일반수학 1",
    "grade": "전체",
    "credit": "3.0",
    "category": "교양필수",
    "time": "월1,월2,월3,금7,금8,금9",
    "place": "5동107A",
    "detail_place": "월1,2,3,금7,8,9(5동107A)",
    "name_pf": "장영호",
    "rate": "상대평가",
    "isWeb": false,
    "bigo": ""
  },
  {
    "dept": "1185283",
    "deptName": "정보통신공학과",
    "sno": "MTH1001-030",
    "subject": "일반수학 1",
    "grade": "전체",
    "credit": "3.0",
    "category": "교양필수",
    "time": "수7,수8,수9,금10,금11,금12",
    "place": "5동107B",
    "detail_place": "수7,8,9,금10,11,12(5동107B)",
    "name_pf": "정찬석",
    "rate": "상대평가",
    "isWeb": false,
    "bigo": ""
  },
  {
    "dept": "1185283",
    "deptName": "정보통신공학과",
    "sno": "MTH1001-031",
    "subject": "일반수학 1",
    "grade": "전체",
    "credit": "3.0",
    "category": "교양필수",
    "time": "화10,화11,화12,금1,금2,금3",
    "place": "5동105A",
    "detail_place": "화10,11,12,금1,2,3(5동105A)",
    "name_pf": "장태수",
    "rate": "상대평가",
    "isWeb": false,
    "bigo": ""
  },
  {
    "dept": "1185283",
    "deptName": "정보통신공학과",
    "sno": "PHY1001-026",
    "subject": "물리학 1",
    "grade": "전체",
    "credit": "3.0",
    "category": "교양필수",
    "time": "월10,월11,월12,수10,수11,수12",
    "place": "5동406",
    "detail_place": "월10,11,12,수10,11,12(5동406)",
    "name_pf": "홍석민",
    "rate": "상대평가",
    "isWeb": false,
    "bigo": ""
  },
  {
    "dept": "1185283",
    "deptName": "정보통신공학과",
    "sno": "PHY1001-027",
    "subject": "물리학 1",
    "grade": "전체",
    "credit": "3.0",
    "category": "교양필수",
    "time": "월13,월14,월15,수13,수14,수15",
    "place": "5동407",
    "detail_place": "월13,14,15,수13,14,15(5동407)",
    "name_pf": "이석목",
    "rate": "상대평가",
    "isWeb": false,
    "bigo": ""
  },
  {
    "dept": "1185283",
    "deptName": "정보통신공학과",
    "sno": "PHY1003-025",
    "subject": "물리학실험 1",
    "grade": "전체",
    "credit": "1.0",
    "category": "교양필수",
    "time": "월1,월2,월3,월4",
    "place": "5동315",
    "detail_place": "월1,2,3,4(5동315)",
    "name_pf": "허남정",
    "rate": "상대평가",
    "isWeb": false,
    "bigo": ""
  },
  {
    "dept": "1185283",
    "deptName": "정보통신공학과",
    "sno": "PHY1003-026",
    "subject": "물리학실험 1",
    "grade": "전체",
    "credit": "1.0",
    "category": "교양필수",
    "time": "화5,화6,화7,화8",
    "place": "5동315",
    "detail_place": "화5,6,7,8(5동315)",
    "name_pf": "김현철",
    "rate": "상대평가",
    "isWeb": false,
    "bigo": ""
  },
  {
    "dept": "1185283",
    "deptName": "정보통신공학과",
    "sno": "PHY1003-027",
    "subject": "물리학실험 1",
    "grade": "전체",
    "credit": "1.0",
    "category": "교양필수",
    "time": "월5,월6,월7,월8",
    "place": "5동315",
    "detail_place": "월5,6,7,8(5동315)",
    "name_pf": "이덕선",
    "rate": "상대평가",
    "isWeb": false,
    "bigo": ""
  },
  {
    "dept": "1184217",
    "deptName": "컴퓨터공학과",
    "sno": "GEB1112-001",
    "subject": "크로스오버 1 : 인간의 탐색",
    "grade": "1",
    "credit": "2.0",
    "category": "교양필수",
    "time": "월4,월5,월6,월7",
    "place": "60주년-101",
    "detail_place": "월4,5,6,7(60주년-101)",
    "name_pf": "정연재",
    "rate": "Pass/Fail",
    "isWeb": false,
    "bigo": "이공계열 학생 수강,"
  },
  {
    "dept": "1184217",
    "deptName": "컴퓨터공학과",
    "sno": "GEB1112-002",
    "subject": "크로스오버 1 : 인간의 탐색",
    "grade": "1",
    "credit": "2.0",
    "category": "교양필수",
    "time": "월9,월10,월11,월12",
    "place": "60주년-101",
    "detail_place": "월9,10,11,12(60주년-101)",
    "name_pf": "정연재",
    "rate": "Pass/Fail",
    "isWeb": false,
    "bigo": "이공계열 학생 수강,"
  },
  {
    "dept": "1184217",
    "deptName": "컴퓨터공학과",
    "sno": "GEB1112-003",
    "subject": "크로스오버 1 : 인간의 탐색",
    "grade": "1",
    "credit": "2.0",
    "category": "교양필수",
    "time": "월4,월5,월6,월7",
    "place": "60주년-107",
    "detail_place": "월4,5,6,7(60주년-107)",
    "name_pf": "도윤정",
    "rate": "Pass/Fail",
    "isWeb": false,
    "bigo": "이공계열 학생 수강,"
  },
  {
    "dept": "1184217",
    "deptName": "컴퓨터공학과",
    "sno": "GEB1112-004",
    "subject": "크로스오버 1 : 인간의 탐색",
    "grade": "1",
    "credit": "2.0",
    "category": "교양필수",
    "time": "월9,월10,월11,월12",
    "place": "60주년-107",
    "detail_place": "월9,10,11,12(60주년-107)",
    "name_pf": "도윤정",
    "rate": "Pass/Fail",
    "isWeb": false,
    "bigo": "이공계열 학생 수강,"
  },
  {
    "dept": "1184217",
    "deptName": "컴퓨터공학과",
    "sno": "GEB1112-005",
    "subject": "크로스오버 1 : 인간의 탐색",
    "grade": "1",
    "credit": "2.0",
    "category": "교양필수",
    "time": "월9,월10,월11,월12",
    "place": "60주년-201",
    "detail_place": "월9,10,11,12(60주년-201)",
    "name_pf": "정영진",
    "rate": "Pass/Fail",
    "isWeb": false,
    "bigo": "이공계열 학생 수강,"
  },
  {
    "dept": "1184217",
    "deptName": "컴퓨터공학과",
    "sno": "GEB1112-006",
    "subject": "크로스오버 1 : 인간의 탐색",
    "grade": "1",
    "credit": "2.0",
    "category": "교양필수",
    "time": "월4,월5,월6,월7",
    "place": "60주년-206",
    "detail_place": "월4,5,6,7(60주년-206)",
    "name_pf": "성동기",
    "rate": "Pass/Fail",
    "isWeb": false,
    "bigo": "이공계열 학생 수강,"
  },
  {
    "dept": "1184217",
    "deptName": "컴퓨터공학과",
    "sno": "GEB1112-007",
    "subject": "크로스오버 1 : 인간의 탐색",
    "grade": "1",
    "credit": "2.0",
    "category": "교양필수",
    "time": "월9,월10,월11,월12",
    "place": "60주년-206",
    "detail_place": "월9,10,11,12(60주년-206)",
    "name_pf": "성동기",
    "rate": "Pass/Fail",
    "isWeb": false,
    "bigo": "이공계열 학생 수강,"
  },
  {
    "dept": "1184217",
    "deptName": "컴퓨터공학과",
    "sno": "GEB1112-008",
    "subject": "크로스오버 1 : 인간의 탐색",
    "grade": "1",
    "credit": "2.0",
    "category": "교양필수",
    "time": "화4,화5,화6,화7",
    "place": "60주년-207",
    "detail_place": "화4,5,6,7(60주년-207)",
    "name_pf": "정연재",
    "rate": "Pass/Fail",
    "isWeb": false,
    "bigo": "이공계열 학생 수강,"
  },
  {
    "dept": "1184217",
    "deptName": "컴퓨터공학과",
    "sno": "GEB1112-009",
    "subject": "크로스오버 1 : 인간의 탐색",
    "grade": "1",
    "credit": "2.0",
    "category": "교양필수",
    "time": "수9,수10,수11,수12",
    "place": "60주년-207",
    "detail_place": "수9,10,11,12(60주년-207)",
    "name_pf": "정영진",
    "rate": "Pass/Fail",
    "isWeb": false,
    "bigo": "이공계열 학생 수강,"
  },
  {
    "dept": "1184217",
    "deptName": "컴퓨터공학과",
    "sno": "GEB1112-010",
    "subject": "크로스오버 1 : 인간의 탐색",
    "grade": "1",
    "credit": "2.0",
    "category": "교양필수",
    "time": "화20,화21,화22,화23",
    "place": "60주년-206",
    "detail_place": "화20,21,22,23(60주년-206)",
    "name_pf": "성동기",
    "rate": "Pass/Fail",
    "isWeb": false,
    "bigo": "미래융합대학 분반,"
  },
  {
    "dept": "1184217",
    "deptName": "컴퓨터공학과",
    "sno": "MTH1001-025",
    "subject": "일반수학 1",
    "grade": "1",
    "credit": "3.0",
    "category": "교양필수",
    "time": "화7,화8,화9,금4,금5,금6",
    "place": "5동106A",
    "detail_place": "화7,8,9,금4,5,6(5동106A)",
    "name_pf": "이춘란",
    "rate": "상대평가",
    "isWeb": false,
    "bigo": ""
  },
  {
    "dept": "1184217",
    "deptName": "컴퓨터공학과",
    "sno": "MTH1001-026",
    "subject": "일반수학 1",
    "grade": "1",
    "credit": "3.0",
    "category": "교양필수",
    "time": "수7,수8,수9,금10,금11,금12",
    "place": "5동106A",
    "detail_place": "수7,8,9,금10,11,12(5동106A)",
    "name_pf": "오명선",
    "rate": "상대평가",
    "isWeb": false,
    "bigo": ""
  },
  {
    "dept": "1184217",
    "deptName": "컴퓨터공학과",
    "sno": "MTH1001-027",
    "subject": "일반수학 1",
    "grade": "1",
    "credit": "3.0",
    "category": "교양필수",
    "time": "화10,화11,화12,금1,금2,금3",
    "place": "5동105B",
    "detail_place": "화10,11,12,금1,2,3(5동105B)",
    "name_pf": "이춘란",
    "rate": "상대평가",
    "isWeb": false,
    "bigo": ""
  },
  {
    "dept": "1184217",
    "deptName": "컴퓨터공학과",
    "sno": "MTH1001-028",
    "subject": "일반수학 1",
    "grade": "1",
    "credit": "3.0",
    "category": "교양필수",
    "time": "월13,월14,월15,수13,수14,수15",
    "place": "5동106B",
    "detail_place": "월13,14,15,수13,14,15(5동106B)",
    "name_pf": "박성화",
    "rate": "상대평가",
    "isWeb": false,
    "bigo": ""
  },
  {
    "dept": "1184217",
    "deptName": "컴퓨터공학과",
    "sno": "PHY1001-023",
    "subject": "물리학 1",
    "grade": "1",
    "credit": "3.0",
    "category": "교양필수",
    "time": "화7,화8,화9,금4,금5,금6",
    "place": "5동406",
    "detail_place": "화7,8,9,금4,5,6(5동406)",
    "name_pf": "김민수",
    "rate": "상대평가",
    "isWeb": false,
    "bigo": ""
  },
  {
    "dept": "1184217",
    "deptName": "컴퓨터공학과",
    "sno": "PHY1001-024",
    "subject": "물리학 1",
    "grade": "1",
    "credit": "3.0",
    "category": "교양필수",
    "time": "월1,월2,월3,수4,수5,수6",
    "place": "5동407",
    "detail_place": "월1,2,3,수4,5,6(5동407)",
    "name_pf": "이재우",
    "rate": "상대평가",
    "isWeb": false,
    "bigo": ""
  },
  {
    "dept": "1184217",
    "deptName": "컴퓨터공학과",
    "sno": "PHY1001-025",
    "subject": "물리학 1",
    "grade": "1",
    "credit": "3.0",
    "category": "교양필수",
    "time": "화4,화5,화6,목7,목8,목9",
    "place": "5동406",
    "detail_place": "화4,5,6,목7,8,9(5동406)",
    "name_pf": "류지현",
    "rate": "상대평가",
    "isWeb": false,
    "bigo": ""
  },
  {
    "dept": "1184217",
    "deptName": "컴퓨터공학과",
    "sno": "PHY1003-021",
    "subject": "물리학실험 1",
    "grade": "1",
    "credit": "1.0",
    "category": "교양필수",
    "time": "화13,화14,화15,화16",
    "place": "5동315",
    "detail_place": "화13,14,15,16(5동315)",
    "name_pf": "이규태",
    "rate": "상대평가",
    "isWeb": false,
    "bigo": ""
  },
  {
    "dept": "1184217",
    "deptName": "컴퓨터공학과",
    "sno": "PHY1003-022",
    "subject": "물리학실험 1",
    "grade": "1",
    "credit": "1.0",
    "category": "교양필수",
    "time": "수9,수10,수11,수12",
    "place": "5동315",
    "detail_place": "수9,10,11,12(5동315)",
    "name_pf": "노재우",
    "rate": "상대평가",
    "isWeb": false,
    "bigo": ""
  },
  {
    "dept": "1184217",
    "deptName": "컴퓨터공학과",
    "sno": "PHY1003-023",
    "subject": "물리학실험 1",
    "grade": "1",
    "credit": "1.0",
    "category": "교양필수",
    "time": "월9,월10,월11,월12",
    "place": "5동315",
    "detail_place": "월9,10,11,12(5동315)",
    "name_pf": "류한열",
    "rate": "상대평가",
    "isWeb": false,
    "bigo": ""
  },
  {
    "dept": "1184217",
    "deptName": "컴퓨터공학과",
    "sno": "PHY1003-024",
    "subject": "물리학실험 1",
    "grade": "1",
    "credit": "1.0",
    "category": "교양필수",
    "time": "월1,월2,월3,월4",
    "place": "5동313",
    "detail_place": "월1,2,3,4(5동313)",
    "name_pf": "김현철",
    "rate": "상대평가",
    "isWeb": false,
    "bigo": ""
  },
  {
    "dept": "1184217",
    "deptName": "컴퓨터공학과",
    "sno": "ACE1312-001",
    "subject": "이산수학",
    "grade": "2",
    "credit": "3.0",
    "category": "교양필수",
    "time": "화1,화2,화3,목4,목5,목6",
    "place": "하-120",
    "detail_place": "화1,2,3,목4,5,6(하-120)",
    "name_pf": "유원희",
    "rate": "상대평가",
    "isWeb": false,
    "bigo": ""
  },
  {
    "dept": "1184217",
    "deptName": "컴퓨터공학과",
    "sno": "ACE1312-002",
    "subject": "이산수학",
    "grade": "2",
    "credit": "3.0",
    "category": "교양필수",
    "time": "월19,월20,월21,월22,월23,월24",
    "place": "하-120",
    "detail_place": "월19,20,21,22,23,24(하-120)",
    "name_pf": "전상표",
    "rate": "상대평가",
    "isWeb": false,
    "bigo": ""
  },
  {
    "dept": "1184217",
    "deptName": "컴퓨터공학과",
    "sno": "ACE1312-003",
    "subject": "이산수학",
    "grade": "2",
    "credit": "3.0",
    "category": "교양필수",
    "time": "월1,월2,월3,수7,수8,수9",
    "place": "하-220,하-120",
    "detail_place": "월1,2,3(하-220) /수7,8,9(하-120)",
    "name_pf": "이연",
    "rate": "상대평가",
    "isWeb": false,
    "bigo": ""
  },
  {
    "dept": "1184217",
    "deptName": "컴퓨터공학과",
    "sno": "ACE1312-004",
    "subject": "이산수학",
    "grade": "2",
    "credit": "3.0",
    "category": "교양필수",
    "time": "월7,월8,월9,수13,수14,수15",
    "place": "하-001,하-120",
    "detail_place": "월7,8,9(하-001) /수13,14,15(하-120)",
    "name_pf": "이연",
    "rate": "상대평가",
    "isWeb": false,
    "bigo": ""
  },
  {
    "dept": "1184217",
    "deptName": "컴퓨터공학과",
    "sno": "ACE2104-003",
    "subject": "통계학",
    "grade": "2",
    "credit": "3.0",
    "category": "교양필수",
    "time": "월16,월17,월18,수4,수5,수6",
    "place": "하-121,하-001",
    "detail_place": "월16,17,18(하-121) /수4,5,6(하-001)",
    "name_pf": "최성용",
    "rate": "상대평가",
    "isWeb": false,
    "bigo": ""
  },
  {
    "dept": "1184217",
    "deptName": "컴퓨터공학과",
    "sno": "ACE2104-004",
    "subject": "통계학",
    "grade": "2",
    "credit": "3.0",
    "category": "교양필수",
    "time": "월19,월20,월21,수7,수8,수9",
    "place": "하-121,하-001",
    "detail_place": "월19,20,21(하-121) /수7,8,9(하-001)",
    "name_pf": "최성용",
    "rate": "상대평가",
    "isWeb": false,
    "bigo": ""
  },
  {
    "dept": "1184217",
    "deptName": "컴퓨터공학과",
    "sno": "ACE2104-005",
    "subject": "통계학",
    "grade": "2",
    "credit": "3.0",
    "category": "교양필수",
    "time": "금10,금11,금12,금13,금14,금15",
    "place": "하-001",
    "detail_place": "금10,11,12,13,14,15(하-001)",
    "name_pf": "김태간",
    "rate": "상대평가",
    "isWeb": false,
    "bigo": ""
  },
  {
    "dept": "1184217",
    "deptName": "컴퓨터공학과",
    "sno": "ACE2106-001",
    "subject": "정수론입문",
    "grade": "2",
    "credit": "3.0",
    "category": "교양필수",
    "time": "월1,월2,월3,금4,금5,금6",
    "place": "하-120,하-220",
    "detail_place": "월1,2,3(하-120) /금4,5,6(하-220)",
    "name_pf": "유자도",
    "rate": "상대평가",
    "isWeb": false,
    "bigo": ""
  },
  {
    "dept": "1184217",
    "deptName": "컴퓨터공학과",
    "sno": "ACE2106-002",
    "subject": "정수론입문",
    "grade": "2",
    "credit": "3.0",
    "category": "교양필수",
    "time": "월4,월5,월6,금1,금2,금3",
    "place": "하-001,하-220",
    "detail_place": "월4,5,6(하-001) /금1,2,3(하-220)",
    "name_pf": "유자도",
    "rate": "상대평가",
    "isWeb": false,
    "bigo": ""
  },
  {
    "dept": "1184217",
    "deptName": "컴퓨터공학과",
    "sno": "ACE2106-003",
    "subject": "정수론입문",
    "grade": "2",
    "credit": "3.0",
    "category": "교양필수",
    "time": "수1,수2,수3,금10,금11,금12",
    "place": "하-222,하-220",
    "detail_place": "수1,2,3(하-222) /금10,11,12(하-220)",
    "name_pf": "유자도",
    "rate": "상대평가",
    "isWeb": false,
    "bigo": ""
  },
  {
    "dept": "1184217",
    "deptName": "컴퓨터공학과",
    "sno": "ACE2106-004",
    "subject": "정수론입문",
    "grade": "2",
    "credit": "3.0",
    "category": "교양필수",
    "time": "수4,수5,수6,금13,금14,금15",
    "place": "하-222,하-220",
    "detail_place": "수4,5,6(하-222) /금13,14,15(하-220)",
    "name_pf": "유자도",
    "rate": "상대평가",
    "isWeb": false,
    "bigo": ""
  }
]