[
  {
    "dept": "1185283",
    "sno": "ACE9501-001",
    "subject": "다학년 연구프로젝트 1",
    "grade": "전체",
    "credit": "1.0",
    "category": "전공선택",
    "time": "월19,월20",
    "place": "7-601",
    "detail_place": "월19,20(7-601)",
    "name_pf": "김학일",
    "rate": "절대평가",
    "isWeb": false,
    "bigo": "영어,English,"
  },
  {
    "dept": "1185283",
    "sno": "ACE9501-002",
    "subject": "다학년 연구프로젝트 1",
    "grade": "전체",
    "credit": "1.0",
    "category": "전공선택",
    "time": "월19,월20",
    "place": "60주년-607",
    "detail_place": "월19,20(60주년-607)",
    "name_pf": "김주형",
    "rate": "절대평가",
    "isWeb": false,
    "bigo": "영어,English,"
  },
  {
    "dept": "1185283",
    "sno": "ACE9501-003",
    "subject": "다학년 연구프로젝트 1",
    "grade": "전체",
    "credit": "1.0",
    "category": "전공선택",
    "time": "월19,월20",
    "place": "60주년-508",
    "detail_place": "월19,20(60주년-508)",
    "name_pf": "이선곤",
    "rate": "Pass/Fail",
    "isWeb": false,
    "bigo": ""
  },
  {
    "dept": "1185283",
    "sno": "ACE9501-004",
    "subject": "다학년 연구프로젝트 1",
    "grade": "전체",
    "credit": "1.0",
    "category": "전공선택",
    "time": "월19,월20",
    "place": "60주년-509",
    "detail_place": "월19,20(60주년-509)",
    "name_pf": "신도형",
    "rate": "Pass/Fail",
    "isWeb": false,
    "bigo": ""
  },
  {
    "dept": "1185283",
    "sno": "ACE9501-005",
    "subject": "다학년 연구프로젝트 1",
    "grade": "전체",
    "credit": "1.0",
    "category": "전공선택",
    "time": "월19,월20",
    "place": "60주년-510",
    "detail_place": "월19,20(60주년-510)",
    "name_pf": "한승우",
    "rate": "Pass/Fail",
    "isWeb": false,
    "bigo": ""
  },
  {
    "dept": "1185283",
    "sno": "ACE9501-006",
    "subject": "다학년 연구프로젝트 1",
    "grade": "전체",
    "credit": "1.0",
    "category": "전공선택",
    "time": "월19,월20",
    "place": "60주년-511",
    "detail_place": "월19,20(60주년-511)",
    "name_pf": "최학남",
    "rate": "Pass/Fail",
    "isWeb": false,
    "bigo": ""
  },
  {
    "dept": "1185283",
    "sno": "ACE9501-007",
    "subject": "다학년 연구프로젝트 1",
    "grade": "전체",
    "credit": "1.0",
    "category": "전공선택",
    "time": "월22,월23",
    "place": "60주년-607",
    "detail_place": "월22,23(60주년-607)",
    "name_pf": "김학일",
    "rate": "Pass/Fail",
    "isWeb": false,
    "bigo": ""
  },
  {
    "dept": "1185283",
    "sno": "ACE9503-001",
    "subject": "다학년 연구프로젝트 3",
    "grade": "전체",
    "credit": "1.0",
    "category": "전공선택",
    "time": "월19,월20",
    "place": "7-601",
    "detail_place": "월19,20(7-601)",
    "name_pf": "김학일",
    "rate": "절대평가",
    "isWeb": false,
    "bigo": "영어,English,"
  },
  {
    "dept": "1185283",
    "sno": "ACE9503-002",
    "subject": "다학년 연구프로젝트 3",
    "grade": "전체",
    "credit": "1.0",
    "category": "전공선택",
    "time": "월19,월20",
    "place": "60주년-607",
    "detail_place": "월19,20(60주년-607)",
    "name_pf": "김주형",
    "rate": "절대평가",
    "isWeb": false,
    "bigo": "영어,English,"
  },
  {
    "dept": "1185283",
    "sno": "ACE9503-003",
    "subject": "다학년 연구프로젝트 3",
    "grade": "전체",
    "credit": "1.0",
    "category": "전공선택",
    "time": "월19,월20",
    "place": "60주년-508",
    "detail_place": "월19,20(60주년-508)",
    "name_pf": "이선곤",
    "rate": "Pass/Fail",
    "isWeb": false,
    "bigo": ""
  },
  {
    "dept": "1185283",
    "sno": "ACE9503-004",
    "subject": "다학년 연구프로젝트 3",
    "grade": "전체",
    "credit": "1.0",
    "category": "전공선택",
    "time": "월19,월20",
    "place": "60주년-509",
    "detail_place": "월19,20(60주년-509)",
    "name_pf": "신도형",
    "rate": "Pass/Fail",
    "isWeb": false,
    "bigo": ""
  },
  {
    "dept": "1185283",
    "sno": "ACE9503-005",
    "subject": "다학년 연구프로젝트 3",
    "grade": "전체",
    "credit": "1.0",
    "category": "전공선택",
    "time": "월19,월20",
    "place": "60주년-510",
    "detail_place": "월19,20(60주년-510)",
    "name_pf": "한승우",
    "rate": "Pass/Fail",
    "isWeb": false,
    "bigo": ""
  },
  {
    "dept": "1185283",
    "sno": "ACE9503-006",
    "subject": "다학년 연구프로젝트 3",
    "grade": "전체",
    "credit": "1.0",
    "category": "전공선택",
    "time": "월19,월20",
    "place": "60주년-511",
    "detail_place": "월19,20(60주년-511)",
    "name_pf": "최학남",
    "rate": "Pass/Fail",
    "isWeb": false,
    "bigo": ""
  },
  {
    "dept": "1185283",
    "sno": "ACE9503-007",
    "subject": "다학년 연구프로젝트 3",
    "grade": "전체",
    "credit": "1.0",
    "category": "전공선택",
    "time": "월22,월23",
    "place": "60주년-607",
    "detail_place": "월22,23(60주년-607)",
    "name_pf": "김학일",
    "rate": "Pass/Fail",
    "isWeb": false,
    "bigo": ""
  },
  {
    "dept": "1185283",
    "sno": "ICE1001-001",
    "subject": "정보통신입문",
    "grade": "전체",
    "credit": "3.0",
    "category": "전공필수",
    "time": "월16,월17,월18,월19,월20,월21",
    "place": "하-232",
    "detail_place": "월16,17,18,19,20,21(하-232)",
    "name_pf": "이종호",
    "rate": "절대평가",
    "isWeb": false,
    "bigo": "영어,English,"
  },
  {
    "dept": "1185283",
    "sno": "ICE1001-002",
    "subject": "정보통신입문",
    "grade": "전체",
    "credit": "3.0",
    "category": "전공필수",
    "time": "화1,화2,화3,목1,목2,목3",
    "place": "하-230",
    "detail_place": "화1,2,3,목1,2,3(하-230)",
    "name_pf": "이승걸",
    "rate": "상대평가",
    "isWeb": false,
    "bigo": ""
  },
  {
    "dept": "1185283",
    "sno": "ICE1001-003",
    "subject": "정보통신입문",
    "grade": "전체",
    "credit": "3.0",
    "category": "전공필수",
    "time": "월10,월11,월12,수10,수11,수12",
    "place": "하-230",
    "detail_place": "월10,11,12,수10,11,12(하-230)",
    "name_pf": "이승걸",
    "rate": "상대평가",
    "isWeb": false,
    "bigo": ""
  },
  {
    "dept": "1185283",
    "sno": "ICE2002-001",
    "subject": "회로이론",
    "grade": "전체",
    "credit": "3.0",
    "category": "전공필수",
    "time": "화7,화8,화9,수7,수8,수9",
    "place": "하-232",
    "detail_place": "화7,8,9,수7,8,9(하-232)",
    "name_pf": "이한호",
    "rate": "상대평가",
    "isWeb": false,
    "bigo": ""
  },
  {
    "dept": "1185283",
    "sno": "ICE2002-002",
    "subject": "회로이론",
    "grade": "전체",
    "credit": "3.0",
    "category": "전공필수",
    "time": "화13,화14,화15,목10,목11,목12",
    "place": "하-230",
    "detail_place": "화13,14,15,목10,11,12(하-230)",
    "name_pf": "변경수",
    "rate": "절대평가",
    "isWeb": false,
    "bigo": "영어,English,"
  },
  {
    "dept": "1185283",
    "sno": "ICE2002-003",
    "subject": "회로이론",
    "grade": "전체",
    "credit": "3.0",
    "category": "전공필수",
    "time": "월13,월14,월15,수13,수14,수15",
    "place": "하-230",
    "detail_place": "월13,14,15,수13,14,15(하-230)",
    "name_pf": "서영교",
    "rate": "상대평가",
    "isWeb": false,
    "bigo": ""
  },
  {
    "dept": "1185283",
    "sno": "ICE2003-001",
    "subject": "전자기학 1",
    "grade": "전체",
    "credit": "3.0",
    "category": "전공필수",
    "time": "월4,월5,월6,수4,수5,수6",
    "place": "하-230",
    "detail_place": "월4,5,6,수4,5,6(하-230)",
    "name_pf": "김대찬",
    "rate": "상대평가",
    "isWeb": false,
    "bigo": "선수,"
  },
  {
    "dept": "1185283",
    "sno": "ICE2003-002",
    "subject": "전자기학 1",
    "grade": "전체",
    "credit": "3.0",
    "category": "전공필수",
    "time": "월13,월14,월15,수13,수14,수15",
    "place": "하-232",
    "detail_place": "월13,14,15,수13,14,15(하-232)",
    "name_pf": "김대찬",
    "rate": "상대평가",
    "isWeb": false,
    "bigo": "선수,"
  },
  {
    "dept": "1185283",
    "sno": "ICE2003-003",
    "subject": "전자기학 1",
    "grade": "전체",
    "credit": "3.0",
    "category": "전공필수",
    "time": "화10,화11,화12,목13,목14,목15",
    "place": "하-230",
    "detail_place": "화10,11,12,목13,14,15(하-230)",
    "name_pf": "오범환",
    "rate": "상대평가",
    "isWeb": false,
    "bigo": "선수,"
  },
  {
    "dept": "1185283",
    "sno": "ICE2004-001",
    "subject": "자료구조론",
    "grade": "전체",
    "credit": "3.0",
    "category": "전공필수",
    "time": "월10,월11,월12,수16,수17,수18",
    "place": "하-232",
    "detail_place": "월10,11,12,수16,17,18(하-232)",
    "name_pf": "김유성",
    "rate": "상대평가",
    "isWeb": false,
    "bigo": "선수,"
  },
  {
    "dept": "1185283",
    "sno": "ICE2004-002",
    "subject": "자료구조론",
    "grade": "전체",
    "credit": "3.0",
    "category": "전공필수",
    "time": "월16,월17,월18,수7,수8,수9",
    "place": "하-230",
    "detail_place": "월16,17,18,수7,8,9(하-230)",
    "name_pf": "김유성",
    "rate": "상대평가",
    "isWeb": false,
    "bigo": "선수,"
  },
  {
    "dept": "1185283",
    "sno": "ICE2004-003",
    "subject": "자료구조론",
    "grade": "전체",
    "credit": "3.0",
    "category": "전공필수",
    "time": "화16,화17,화18,목16,목17,목18",
    "place": "60주년-108",
    "detail_place": "화16,17,18,목16,17,18(60주년-108)",
    "name_pf": "이채은",
    "rate": "상대평가",
    "isWeb": false,
    "bigo": "선수,"
  },
  {
    "dept": "1185283",
    "sno": "ICE2004-004",
    "subject": "자료구조론",
    "grade": "전체",
    "credit": "3.0",
    "category": "전공필수",
    "time": "화16,화17,화18,목16,목17,목18",
    "place": "60주년-108",
    "detail_place": "화16,17,18,목16,17,18(60주년-108)",
    "name_pf": "이채은",
    "rate": "상대평가",
    "isWeb": false,
    "bigo": "선수,"
  },
  {
    "dept": "1185283",
    "sno": "ICE2006-001",
    "subject": "정보통신기초설계/실습 1",
    "grade": "전체",
    "credit": "1.0",
    "category": "전공필수",
    "time": "월4,월5,월6,월7",
    "place": "하-426",
    "detail_place": "월4,5,6,7(하-426)",
    "name_pf": "김춘우",
    "rate": "상대평가",
    "isWeb": false,
    "bigo": ""
  },
  {
    "dept": "1185283",
    "sno": "ICE2006-002",
    "subject": "정보통신기초설계/실습 1",
    "grade": "전체",
    "credit": "1.0",
    "category": "전공필수",
    "time": "월10,월11,월12,월13",
    "place": "하-426",
    "detail_place": "월10,11,12,13(하-426)",
    "name_pf": "박인규",
    "rate": "상대평가",
    "isWeb": false,
    "bigo": ""
  },
  {
    "dept": "1185283",
    "sno": "ICE2006-003",
    "subject": "정보통신기초설계/실습 1",
    "grade": "전체",
    "credit": "1.0",
    "category": "전공필수",
    "time": "화4,화5,화6,화7",
    "place": "하-426",
    "detail_place": "화4,5,6,7(하-426)",
    "name_pf": "박대영",
    "rate": "상대평가",
    "isWeb": false,
    "bigo": ""
  },
  {
    "dept": "1185283",
    "sno": "ICE2006-004",
    "subject": "정보통신기초설계/실습 1",
    "grade": "전체",
    "credit": "1.0",
    "category": "전공필수",
    "time": "화10,화11,화12,화13",
    "place": "하-426",
    "detail_place": "화10,11,12,13(하-426)",
    "name_pf": "이채은",
    "rate": "상대평가",
    "isWeb": false,
    "bigo": ""
  },
  {
    "dept": "1185283",
    "sno": "ICE2006-005",
    "subject": "정보통신기초설계/실습 1",
    "grade": "전체",
    "credit": "1.0",
    "category": "전공필수",
    "time": "수4,수5,수6,수7",
    "place": "하-426",
    "detail_place": "수4,5,6,7(하-426)",
    "name_pf": "서영교",
    "rate": "상대평가",
    "isWeb": false,
    "bigo": ""
  },
  {
    "dept": "1185283",
    "sno": "ICE2006-006",
    "subject": "정보통신기초설계/실습 1",
    "grade": "전체",
    "credit": "1.0",
    "category": "전공필수",
    "time": "목4,목5,목6,목7",
    "place": "하-426",
    "detail_place": "목4,5,6,7(하-426)",
    "name_pf": "변경수",
    "rate": "상대평가",
    "isWeb": false,
    "bigo": ""
  },
  {
    "dept": "1185283",
    "sno": "ICE2006-007",
    "subject": "정보통신기초설계/실습 1",
    "grade": "전체",
    "credit": "1.0",
    "category": "전공필수",
    "time": "금4,금5,금6,금7",
    "place": "하-426",
    "detail_place": "금4,5,6,7(하-426)",
    "name_pf": "변경수",
    "rate": "상대평가",
    "isWeb": false,
    "bigo": ""
  },
  {
    "dept": "1185283",
    "sno": "ICE3002-001",
    "subject": "확률변수론",
    "grade": "전체",
    "credit": "3.0",
    "category": "전공선택",
    "time": "수10,수11,수12,금4,금5,금6",
    "place": "하-232",
    "detail_place": "수10,11,12,금4,5,6(하-232)",
    "name_pf": "김춘우",
    "rate": "상대평가",
    "isWeb": false,
    "bigo": ""
  },
  {
    "dept": "1185283",
    "sno": "ICE3002-002",
    "subject": "확률변수론",
    "grade": "전체",
    "credit": "3.0",
    "category": "전공선택",
    "time": "화13,화14,화15,목13,목14,목15",
    "place": "하-232",
    "detail_place": "화13,14,15,목13,14,15(하-232)",
    "name_pf": "유상조",
    "rate": "상대평가",
    "isWeb": false,
    "bigo": ""
  },
  {
    "dept": "1185283",
    "sno": "ICE3004-001",
    "subject": "반도체소자",
    "grade": "전체",
    "credit": "3.0",
    "category": "전공선택",
    "time": "월7,월8,월9,금1,금2,금3",
    "place": "하-232",
    "detail_place": "월7,8,9,금1,2,3(하-232)",
    "name_pf": "서영교",
    "rate": "절대평가",
    "isWeb": false,
    "bigo": "영어,English,"
  },
  {
    "dept": "1185283",
    "sno": "ICE3005-001",
    "subject": "전자회로 2",
    "grade": "전체",
    "credit": "3.0",
    "category": "전공선택",
    "time": "화16,화17,화18,목4,목5,목6",
    "place": "하-207",
    "detail_place": "화16,17,18,목4,5,6(하-207)",
    "name_pf": "변경수",
    "rate": "절대평가",
    "isWeb": false,
    "bigo": "영어,English,선수,"
  },
  {
    "dept": "1185283",
    "sno": "ICE3008-001",
    "subject": "전파공학",
    "grade": "전체",
    "credit": "3.0",
    "category": "전공선택",
    "time": "월10,월11,월12,화7,화8,화9",
    "place": "하-207",
    "detail_place": "월10,11,12,화7,8,9(하-207)",
    "name_pf": "김덕경",
    "rate": "상대평가",
    "isWeb": false,
    "bigo": ""
  },
  {
    "dept": "1185283",
    "sno": "ICE3008-002",
    "subject": "전파공학",
    "grade": "전체",
    "credit": "3.0",
    "category": "전공선택",
    "time": "월13,월14,월15,화13,화14,화15",
    "place": "하-207",
    "detail_place": "월13,14,15,화13,14,15(하-207)",
    "name_pf": "박대영",
    "rate": "상대평가",
    "isWeb": false,
    "bigo": ""
  },
  {
    "dept": "1185283",
    "sno": "ICE3013-001",
    "subject": "시스템프로그래밍",
    "grade": "전체",
    "credit": "3.0",
    "category": "전공선택",
    "time": "화1,화2,화3,목4,목5,목6",
    "place": "하-424",
    "detail_place": "화1,2,3,목4,5,6(하-424)",
    "name_pf": "김기창",
    "rate": "절대평가",
    "isWeb": false,
    "bigo": "영어,English,"
  },
  {
    "dept": "1185283",
    "sno": "ICE3013-002",
    "subject": "시스템프로그래밍",
    "grade": "전체",
    "credit": "3.0",
    "category": "전공선택",
    "time": "화4,화5,화6,수1,수2,수3",
    "place": "하-424",
    "detail_place": "화4,5,6,수1,2,3(하-424)",
    "name_pf": "김기창",
    "rate": "절대평가",
    "isWeb": false,
    "bigo": "영어,English,"
  },
  {
    "dept": "1185283",
    "sno": "ICE3013-003",
    "subject": "시스템프로그래밍",
    "grade": "전체",
    "credit": "3.0",
    "category": "전공선택",
    "time": "수4,수5,수6,목1,목2,목3",
    "place": "하-424",
    "detail_place": "수4,5,6,목1,2,3(하-424)",
    "name_pf": "김기창",
    "rate": "절대평가",
    "isWeb": false,
    "bigo": "영어,English,"
  },
  {
    "dept": "1185283",
    "sno": "ICE3015-001",
    "subject": "임베디드시스템설계",
    "grade": "전체",
    "credit": "4.0",
    "category": "전공선택",
    "time": "화4,화5,화6,수4,수5,수6,수10,수11,수12,수13",
    "place": "하-207,하-424",
    "detail_place": "화4,5,6,수4,5,6(하-207) /수10,11,12,13(하-424)",
    "name_pf": "박재현",
    "rate": "상대평가",
    "isWeb": false,
    "bigo": "선수,"
  },
  {
    "dept": "1185283",
    "sno": "ICE3017-001",
    "subject": "광통신공학설계",
    "grade": "전체",
    "credit": "4.0",
    "category": "전공선택",
    "time": "화4,화5,화6,목4,목5,목6,금4,금5,금6,금7",
    "place": "하-230,하-424",
    "detail_place": "화4,5,6,목4,5,6(하-230) /금4,5,6,7(하-424)",
    "name_pf": "오범환",
    "rate": "상대평가",
    "isWeb": false,
    "bigo": ""
  },
  {
    "dept": "1185283",
    "sno": "ICE3017-002",
    "subject": "광통신공학설계",
    "grade": "전체",
    "credit": "4.0",
    "category": "전공선택",
    "time": "화4,화5,화6,목4,목5,목6,금10,금11,금12,금13",
    "place": "하-230,하-424",
    "detail_place": "화4,5,6,목4,5,6(하-230) /금10,11,12,13(하-424)",
    "name_pf": "오범환",
    "rate": "상대평가",
    "isWeb": false,
    "bigo": ""
  },
  {
    "dept": "1185283",
    "sno": "ICE4001-001",
    "subject": "광자공학기초",
    "grade": "전체",
    "credit": "3.0",
    "category": "전공선택",
    "time": "화10,화11,화12,목10,목11,목12",
    "place": "하-232",
    "detail_place": "화10,11,12,목10,11,12(하-232)",
    "name_pf": "이승걸",
    "rate": "상대평가",
    "isWeb": false,
    "bigo": ""
  },
  {
    "dept": "1185283",
    "sno": "ICE4005-001",
    "subject": "디지털시스템설계",
    "grade": "전체",
    "credit": "4.0",
    "category": "전공선택",
    "time": "화10,화11,화12,수10,수11,수12,목16,목17,목18,목19",
    "place": "하-002,하-422",
    "detail_place": "화10,11,12,수10,11,12(하-002) /목16,17,18,19(하-422)",
    "name_pf": "이한호",
    "rate": "상대평가",
    "isWeb": false,
    "bigo": "선수,"
  },
  {
    "dept": "1185283",
    "sno": "ICE4005-002",
    "subject": "디지털시스템설계",
    "grade": "전체",
    "credit": "4.0",
    "category": "전공선택",
    "time": "화7,화8,화9,수19,수20,수21,수22,목10,목11,목12",
    "place": "하-002,하-424,하-002",
    "detail_place": "화7,8,9(하-002) /수19,20,21,22(하-424) /목10,11,12(하-002)",
    "name_pf": "이채은",
    "rate": "상대평가",
    "isWeb": false,
    "bigo": "선수,"
  },
  {
    "dept": "1185283",
    "sno": "ICE4009-001",
    "subject": "디지털통신시스템설계",
    "grade": "전체",
    "credit": "4.0",
    "category": "전공선택",
    "time": "월1,월2,월3,월4,월16,월17,월18,화13,화14,화15",
    "place": "하-424,하-207",
    "detail_place": "월1,2,3,4(하-424) /월16,17,18,화13,14,15(하-207)",
    "name_pf": "김덕경",
    "rate": "상대평가",
    "isWeb": false,
    "bigo": "선수,"
  },
  {
    "dept": "1185283",
    "sno": "ICE4009-002",
    "subject": "디지털통신시스템설계",
    "grade": "전체",
    "credit": "4.0",
    "category": "전공선택",
    "time": "월16,월17,월18,화13,화14,화15,목5,목6,목7,목8",
    "place": "하-002,하-422",
    "detail_place": "월16,17,18,화13,14,15(하-002) /목5,6,7,8(하-422)",
    "name_pf": "김덕경",
    "rate": "상대평가",
    "isWeb": false,
    "bigo": "선수,"
  },
  {
    "dept": "1185283",
    "sno": "ICE4024-001",
    "subject": "정보통신종합설계",
    "grade": "전체",
    "credit": "3.0",
    "category": "전공필수",
    "time": "수15,수16,수17,수18,토4,토5,토6,토7",
    "place": "하-503",
    "detail_place": "수15,16,17,18,토4,5,6,7(하-503)",
    "name_pf": "박대영,최학남",
    "rate": "Pass/Fail",
    "isWeb": false,
    "bigo": ""
  },
  {
    "dept": "1185283",
    "sno": "ICE4024-002",
    "subject": "정보통신종합설계",
    "grade": "전체",
    "credit": "3.0",
    "category": "전공필수",
    "time": "수15,수16,수17,수18,토4,토5,토6,토7",
    "place": "하-414",
    "detail_place": "수15,16,17,18,토4,5,6,7(하-414)",
    "name_pf": "유상조,변경수",
    "rate": "Pass/Fail",
    "isWeb": false,
    "bigo": ""
  },
  {
    "dept": "1185283",
    "sno": "ICE4024-003",
    "subject": "정보통신종합설계",
    "grade": "전체",
    "credit": "3.0",
    "category": "전공필수",
    "time": "수15,수16,수17,수18,토4,토5,토6,토7",
    "place": "하-002",
    "detail_place": "수15,16,17,18,토4,5,6,7(하-002)",
    "name_pf": "김학일,박인규",
    "rate": "Pass/Fail",
    "isWeb": false,
    "bigo": ""
  },
  {
    "dept": "1185283",
    "sno": "ICE4024-004",
    "subject": "정보통신종합설계",
    "grade": "전체",
    "credit": "3.0",
    "category": "전공필수",
    "time": "수15,수16,수17,수18,토4,토5,토6,토7",
    "place": "하-501",
    "detail_place": "수15,16,17,18,토4,5,6,7(하-501)",
    "name_pf": "이한호,이채은",
    "rate": "Pass/Fail",
    "isWeb": false,
    "bigo": ""
  },
  {
    "dept": "1185283",
    "sno": "ICE4024-005",
    "subject": "정보통신종합설계",
    "grade": "전체",
    "credit": "3.0",
    "category": "전공필수",
    "time": "수15,수16,수17,수18,토4,토5,토6,토7",
    "place": "하-424",
    "detail_place": "수15,16,17,18,토4,5,6,7(하-424)",
    "name_pf": "김유성,김기창",
    "rate": "Pass/Fail",
    "isWeb": false,
    "bigo": ""
  },
  {
    "dept": "1185283",
    "sno": "ICE4024-006",
    "subject": "정보통신종합설계",
    "grade": "전체",
    "credit": "3.0",
    "category": "전공필수",
    "time": "수15,수16,수17,수18,토4,토5,토6,토7",
    "place": "하-426",
    "detail_place": "수15,16,17,18,토4,5,6,7(하-426)",
    "name_pf": "이승걸,오범환",
    "rate": "Pass/Fail",
    "isWeb": false,
    "bigo": ""
  },
  {
    "dept": "1185283",
    "sno": "ICE4024-007",
    "subject": "정보통신종합설계",
    "grade": "전체",
    "credit": "3.0",
    "category": "전공필수",
    "time": "수15,수16,수17,수18,토4,토5,토6,토7",
    "place": "하-003",
    "detail_place": "수15,16,17,18,토4,5,6,7(하-003)",
    "name_pf": "박재현,김덕경",
    "rate": "Pass/Fail",
    "isWeb": false,
    "bigo": ""
  },
  {
    "dept": "1185283",
    "sno": "ICE4025-001",
    "subject": "인터넷프로토콜",
    "grade": "전체",
    "credit": "3.0",
    "category": "전공선택",
    "time": "월7,월8,월9,화7,화8,화9",
    "place": "하-230",
    "detail_place": "월7,8,9,화7,8,9(하-230)",
    "name_pf": "유상조",
    "rate": "상대평가",
    "isWeb": false,
    "bigo": ""
  },
  {
    "dept": "1185283",
    "sno": "ICE4027-001",
    "subject": "디지털영상처리설계",
    "grade": "전체",
    "credit": "4.0",
    "category": "전공선택",
    "time": "수1,수2,수3,목1,목2,목3,목13,목14,목15,목16",
    "place": "하-232,하-424",
    "detail_place": "수1,2,3,목1,2,3(하-232) /목13,14,15,16(하-424)",
    "name_pf": "김학일,최학남",
    "rate": "절대평가",
    "isWeb": false,
    "bigo": "영어,English,선수,"
  },
  {
    "dept": "1185283",
    "sno": "ICE4029-001",
    "subject": "모바일응용소프트웨어설계",
    "grade": "전체",
    "credit": "4.0",
    "category": "전공선택",
    "time": "화10,화11,화12,목10,목11,목12,금4,금5,금6,금7",
    "place": "하-207,하-422",
    "detail_place": "화10,11,12,목10,11,12(하-207) /금4,5,6,7(하-422)",
    "name_pf": "박인규",
    "rate": "상대평가",
    "isWeb": false,
    "bigo": ""
  },
  {
    "dept": "1185283",
    "sno": "ICE4101-001",
    "subject": "인공지능 응용시스템",
    "grade": "전체",
    "credit": "3.0",
    "category": "전공선택",
    "time": "월10,월11,월12,월13,목19,목20,목21,목22",
    "place": "7-601",
    "detail_place": "월10,11,12,13,목19,20,21,22(7-601)",
    "name_pf": "김학일,최학남",
    "rate": "상대평가",
    "isWeb": false,
    "bigo": ""
  },
  {
    "dept": "1185283",
    "sno": "ICE4103-001",
    "subject": "소프트웨어공학",
    "grade": "전체",
    "credit": "3.0",
    "category": "전공선택",
    "time": "금9,금10,금11,금12,금13,금14,금15,금16",
    "place": "하-422",
    "detail_place": "금9,10,11,12,13,14,15,16(하-422)",
    "name_pf": "이은진",
    "rate": "상대평가",
    "isWeb": false,
    "bigo": ""
  },
  {
    "dept": "1185283",
    "sno": "ICE4124-001",
    "subject": "정보통신 종합설계(NCS 과정)",
    "grade": "전체",
    "credit": "3.0",
    "category": "전공선택",
    "time": "금19,금20,금21,금22,토4,토5,토6,토7",
    "place": "2남229",
    "detail_place": "금19,20,21,22,토4,5,6,7(2남229)",
    "name_pf": "김학일",
    "rate": "Pass/Fail",
    "isWeb": false,
    "bigo": ""
  },
  {
    "dept": "1185283",
    "sno": "ICE4400-001",
    "subject": "기업연계형 정보통신시스템",
    "grade": "전체",
    "credit": "3.0",
    "category": "전공선택",
    "time": "수19,수20,수21,토1,토2,토3",
    "place": "하-232",
    "detail_place": "수19,20,21,토1,2,3(하-232)",
    "name_pf": "박재현",
    "rate": "상대평가",
    "isWeb": false,
    "bigo": ""
  }
]